{"[deleted]": {"p1v0t": "2021-06-20 - PERM-BANNED", "nunqy": "2021-05-17 - PERM-BANNED"}, "NEMOTHEFISH23": {"ooitj": "2021-06-09 - PERM-BANNED"}, "Zorbithia": {"oc6zq": "2021-05-29 - BANNED - 30 days."}, "p0isoNz": {"p18ll": "2021-06-19 - BANNED - 30 days."}, "FriendlyListen8": {"o0koj": "2021-05-19 - PERM-BANNED"}, "sun_of_darkness": {"oxbna": "2021-06-16 - PERM-BANNED"}, "spokes263": {"on7f8": "2021-06-08 - PERM-BANNED"}, "FelixJonson": {"p57e6": "2021-06-22 - PERM-BANNED"}, "Sugamalia": {"owpns": "2021-06-16 - PERM-BANNED"}, "TheRowdyRaven": {"p1v0t": "2021-06-20 - PERM-BANNED"}, "Moser98": {"npj9e": "2021-05-15 - PERM-BANNED"}, "GhostViper56": {"npr69": "2021-05-15 - PERM-BANNED"}, "Draven2Op": {"ohv8j": "2021-06-03 - PERM-BANNED"}, "Rickaay_123": {"oneak": "2021-06-08 - PERM-BANNED"}, "SixlmpossibleThings9": {"o658p": "2021-05-24 - PERM-BANNED"}, "pheelz___": {"pkaxy": "2021-06-30 - PERM-BANNED"}, "Leashed-mode": {"ohi48": "2021-06-03 - PERM-BANNED"}, "Apophis90": {"p8pbu": "2021-06-24 - PERM-BANNED"}, "saturnm22": {"on6zv": "2021-06-08 - PERM-BANNED"}, "12Iona": {"obaxt": "2021-05-28 - PERM-BANNED"}, "strngerkid": {"ovai1": "2021-06-14 - PERM-BANNED"}, "Rstraight32": {"p0fe6": "2021-06-18 - PERM-BANNED"}, "Uncrownedt": {"o0kcs": "2021-05-19 - PERM-BANNED"}, "Altruistic-Pay-3101": {"p09mv": "2021-06-18 - PERM-BANNED"}, "Then_Arachnid5515": {"ou9af": "2021-06-13 - PERM-BANNED"}, "Such_Office_3655": {"owkxa": "2021-06-15 - PERM-BANNED"}, "Kevin3358": {"p5f4y": "2021-06-23 - PERM-BANNED"}, "jtareenk": {"oqh3q": "2021-06-10 - PERM-BANNED"}, "spoof0x": {"o9kck": "2021-05-27 - PERM-BANNED"}, "luvmygolden_13": {"onrno": "2021-06-08 - PERM-BANNED"}, "sambamapangala": {"p0i02": "2021-06-18 - PERM-BANNED"}, "qpcoins": {"ohgl6": "2021-06-03 - BANNED - 14 days."}, "nmrh31": {"o0uss": "2021-05-19 - PERM-BANNED", "o0see": "2021-05-19 - PERM-BANNED"}, "O___7": {"p0nfg": "2021-06-19 - PERM-BANNED"}, "Affectionate-Sleep85": {"oru95": "2021-06-11 - PERM-BANNED"}, "awoere": {"okr3o": "2021-06-06 - PERM-BANNED"}, "t80__n": {"oqb7q": "2021-06-10 - PERM-BANNED"}, "badgirl354": {"ntuco": "2021-05-15 - PERM-BANNED"}, "Jgichiriri5": {"p8cm2": "2021-06-24 - PERM-BANNED"}, "ToS_Definition_Bot": {"nszbm": "2021-05-15 - BANNED - 1 days."}, "HxMythh": {"opzpi": "2021-06-10 - PERM-BANNED", "ox2w3": "2021-06-16 - CHANGED BAN - 30 days."}, "AutoModerator": {"o1qo5": "2021-05-20 - PERM-BANNED"}, "Burgersteelers": {"osj75": "2021-06-12 - PERM-BANNED"}, "mikeyjai": {"o9lke": "2021-05-27 - PERM-BANNED"}, "Omfgimaweirdo": {"olgju": "2021-06-06 - PERM-BANNED"}, "No_Willingness_865": {"oal9a": "2021-05-27 - PERM-BANNED"}, "JakesPieterse": {"omzwk": "2021-06-07 - PERM-BANNED"}, "ssaammaayyy": {"oj2wu": "2021-06-04 - PERM-BANNED"}, "ordinary_redditor_": {"nvumd": "2021-05-16 - PERM-BANNED"}, "Furryoldladytoenails": {"o3lw6": "2021-05-22 - PERM-BANNED"}, "VisumDrums": {"p8d2d": "2021-06-24 - PERM-BANNED"}, "conspiracytheoryfan": {"pjvpf": "2021-06-29 - PERM-BANNED"}, "Lonely-Milk9135": {"o20p4": "2021-05-20 - PERM-BANNED"}, "Appropriate-Till-875": {"ol18c": "2021-06-06 - PERM-BANNED"}, "BackgroundComedian79": {"o5sn3": "2021-05-23 - PERM-BANNED"}, "aking1230981": {"o7ry2": "2021-05-25 - PERM-BANNED"}, "kai-zar": {"pi8tm": "2021-06-28 - PERM-BANNED"}, "Fitnessgodness101": {"o5id4": "2021-05-23 - PERM-BANNED"}, "DashCantPlay": {"pb6oy": "2021-06-25 - PERM-BANNED"}, "corporiz": {"orjmn": "2021-06-11 - PERM-BANNED"}, "ThebigBlyats": {"o5idl": "2021-05-23 - PERM-BANNED"}, "pianogirl282": {"nu8we": "2021-05-15 - PERM-BANNED"}, "robertrucker": {"o9457": "2021-05-26 - PERM-BANNED"}, "chiefredbeardd": {"pj2rx": "2021-06-29 - PERM-BANNED"}, "Lopsided_Morning": {"o0u66": "2021-05-19 - PERM-BANNED"}, "KingExile67": {"ofsdv": "2021-06-01 - PERM-BANNED"}, "Mammoth-Recording-14": {"o1vqr": "2021-05-20 - PERM-BANNED"}, "AnInterestingUser23": {"okh5u": "2021-06-05 - PERM-BANNED"}, "Diam0073": {"olbrv": "2021-06-06 - BANNED - 30 days."}, "Justinderaeveryday": {"ouzva": "2021-06-14 - PERM-BANNED"}, "D3ADEY3Z": {"o9yd7": "2021-05-27 - PERM-BANNED"}, "bmin005": {"npkof": "2021-05-15 - PERM-BANNED"}, "Ellaoptionsfx": {"o4uzr": "2021-05-23 - PERM-BANNED"}, "Tcaldwell1991": {"od9a0": "2021-05-30 - CHANGED BAN - 30 days.", "od92c": "2021-05-30 - BANNED - 7 days.", "ofmmq": "2021-06-01 - PERM-BANNED"}, "Squeeksz506": {"okjfv": "2021-06-05 - PERM-BANNED"}, "WiseUp2RiseUp": {"od98y": "2021-05-30 - BANNED - 30 days."}, "PlayboiShanti": {"ondhj": "2021-06-08 - PERM-BANNED"}, "ThickMusician": {"p7fij": "2021-06-24 - PERM-BANNED"}, "Nice-Commission3154": {"o8bis": "2021-05-25 - PERM-BANNED"}, "Big_Amphibian_3762": {"opzp5": "2021-06-10 - PERM-BANNED"}, "MeeMeeCandy777": {"ot3vw": "2021-06-12 - PERM-BANNED"}, "ShaeHynes": {"ojamp": "2021-06-04 - PERM-BANNED"}, "TasiaParish": {"o3kt5": "2021-05-22 - PERM-BANNED"}, "CrackOfDon88": {"okpg7": "2021-06-05 - PERM-BANNED"}, "goodtimeshaxr": {"o3nbx": "2021-05-22 - PERM-BANNED"}, "LeoSheltn": {"obwec": "2021-05-29 - PERM-BANNED"}, "Loud-Chipmunk4166": {"obg5o": "2021-05-28 - PERM-BANNED"}, "HealTheSOUL": {"onmdz": "2021-06-08 - PERM-BANNED"}, "RussianRambo911": {"pkmzc": "2021-06-30 - PERM-BANNED"}, "AccordingFill": {"nunqy": "2021-05-15 - PERM-BANNED"}}